openzwavemqtt/__init__.py
openzwavemqtt/base.py
openzwavemqtt/const.py
openzwavemqtt/exceptions.py
openzwavemqtt/manager.py
openzwavemqtt/options.py
openzwavemqtt/models/__init__.py
openzwavemqtt/models/command_class.py
openzwavemqtt/models/instance.py
openzwavemqtt/models/instance_statistics.py
openzwavemqtt/models/instance_status.py
openzwavemqtt/models/node.py
openzwavemqtt/models/node_association.py
openzwavemqtt/models/node_child_base.py
openzwavemqtt/models/node_instance.py
openzwavemqtt/models/node_statistics.py
openzwavemqtt/models/value.py
openzwavemqtt/util/__init__.py
openzwavemqtt/util/lock.py
openzwavemqtt/util/mqtt_client.py
openzwavemqtt/util/node.py
python_openzwave_mqtt-1.4.0.dist-info/LICENSE
python_openzwave_mqtt-1.4.0.dist-info/METADATA
python_openzwave_mqtt-1.4.0.dist-info/WHEEL
python_openzwave_mqtt-1.4.0.dist-info/top_level.txt
python_openzwave_mqtt-1.4.0.dist-info/RECORD
