Metadata-Version: 2.1
Name: python-openzwave-mqtt
Version: 1.4.0
Summary: Converts MQTT messages from qt-openzwave into Python objects and events
Home-page: https://github.com/cgarwood/python-openzwave-mqtt
Author: Charles Garwood
Author-email: cgarwood@gmail.com
License: UNKNOWN
Download-URL: https://github.com/cgarwood/python-openzwave-mqtt
Platform: UNKNOWN
Classifier: Development Status :: 4 - Beta
Classifier: Intended Audience :: Developers
Classifier: Natural Language :: English
Classifier: Programming Language :: Python :: 3
Classifier: Programming Language :: Python :: 3.7
Classifier: Programming Language :: Python :: 3.8
Classifier: Topic :: Home Automation
Requires-Python: >=3.7
Provides-Extra: mqtt-client
Requires-Dist: asyncio-mqtt ; extra == 'mqtt-client'
